tabular_tool_kit
