Metadata-Version: 2.1
Name: tabular_tool_kit
Version: 1.0.3
Summary: CSV处理工具包 (CSV Process Tool Kit)
Home-page: https://github.com/KallerIsaac10086/tabular_tool_kit
Author: Kaller
Author-email: sjy84789@gmail.com
Classifier: Programming Language :: Python :: 3
Classifier: License :: OSI Approved :: Apache Software License
Classifier: Operating System :: OS Independent
Requires-Python: >=3.6
License-File: LICENSE
Requires-Dist: pandas>=1.0.0
Requires-Dist: tqdm>=4.45.0
Requires-Dist: openpyxl>=3.0.0
Requires-Dist: XlsxWriter>=3.2.0
